JCompare/__init__.py
JCompare/compare.py
JCompare/folder.py
JCompare/hash.py
JCompare/mcs.py
JCompare/metrics.py
JCompare/mode.py
JCompare/similarity.py
JCompare/tree.py
JCompare-0.0.1.2.dist-info/LICENSE
JCompare-0.0.1.2.dist-info/METADATA
JCompare-0.0.1.2.dist-info/WHEEL
JCompare-0.0.1.2.dist-info/top_level.txt
JCompare-0.0.1.2.dist-info/RECORD
