Metadata-Version: 2.1
Name: JCompare
Version: 0.0.1.2
Summary: A folder compare utility.
Home-page: https://github.com/UFervor/JCompare
Author: _Fervor_
Requires-Python: >=3.10.0
License-File: LICENSE
Requires-Dist: tqdm
Requires-Dist: patool
Requires-Dist: dict-hash
Requires-Dist: zstandard
Requires-Dist: brotli
